akdpy/__init__.py
akdpy/system.py
akdpy-0.0.3.dist-info/METADATA
akdpy-0.0.3.dist-info/WHEEL
akdpy-0.0.3.dist-info/top_level.txt
akdpy-0.0.3.dist-info/RECORD
