Metadata-Version: 2.1
Name: akdpy
Version: 0.0.3
Summary: A small example package
Author: akdogantech
Classifier: Programming Language :: Python :: 3
Classifier: License :: OSI Approved :: MIT License
Classifier: Operating System :: OS Independent
Requires-Dist: psutil
